passthrough/__init__.py
passthrough/exc.py
passthrough/extensions/__init__.py
passthrough/extensions/exm/__init__.py
passthrough/extensions/exm/lid.py
passthrough/extensions/file/__init__.py
passthrough/extensions/pt/__init__.py
passthrough/extensions/pt/context.py
passthrough/extensions/pt/datetime.py
passthrough/extensions/pt/misc.py
passthrough/extensions/pt/vid.py
passthrough/label_tools.py
passthrough/state.py
passthrough/template.py
passthrough-0.3.2.dist-info/entry_points.txt
passthrough-0.3.2.dist-info/LICENSE
passthrough-0.3.2.dist-info/WHEEL
passthrough-0.3.2.dist-info/METADATA
passthrough-0.3.2.dist-info/RECORD
